{
  "travel_index": 66,
  "menu_index": 88,
  "day": 12,
  "today_words": {
    "travel": [
      {
        "word": "キャンプ",
        "kana": "キャンプ",
        "meaning": "露營",
        "level": "N4"
      },
      {
        "word": "スケジュール",
        "kana": "スケジュール",
        "meaning": "行程表、計畫",
        "level": "N4"
      },
      {
        "word": "世界旅行",
        "kana": "せかいりょこう",
        "meaning": "環遊世界",
        "level": "N4"
      },
      {
        "word": "地図",
        "kana": "ちず",
        "meaning": "地圖",
        "level": "N4"
      },
      {
        "word": "泊まる",
        "kana": "とまる",
        "meaning": "住、留宿",
        "level": "N4"
      },
      {
        "word": "パスポート",
        "kana": "パスポート",
        "meaning": "護照",
        "level": "N4"
      }
    ],
    "menu": [
      {
        "word": "にがい",
        "kana": "にがい",
        "meaning": "苦",
        "level": "N4"
      },
      {
        "word": "メニュー",
        "kana": "メニュー",
        "meaning": "菜單",
        "level": "N4"
      },
      {
        "word": "ごちそう（を）する",
        "kana": "ごちそう（を）する",
        "meaning": "請客、招待",
        "level": "N4"
      },
      {
        "word": "わかす",
        "kana": "わかす",
        "meaning": "燒開水",
        "level": "N4"
      },
      {
        "word": "冷やす",
        "kana": "ひやす",
        "meaning": "冷卻、冰鎮",
        "level": "N4"
      },
      {
        "word": "混ぜる",
        "kana": "まぜる",
        "meaning": "混合、攪拌",
        "level": "N4"
      },
      {
        "word": "むく",
        "kana": "むく",
        "meaning": "削、剝皮",
        "level": "N4"
      },
      {
        "word": "お皿",
        "kana": "おさら",
        "meaning": "盤子",
        "level": "N4"
      }
    ]
  },
  "last_sent_date": "2026-06-25",
  "last_review_date": "2026-06-24",
  "today_day": 11
}